[
    {
        "dongtaiid": "899823385454837766",
        "status": 0
    },
    {
        "dongtaiid": "899767026855182337",
        "status": 0
    },
    {
        "dongtaiid": "899725090816524292",
        "status": 0
    },
    {
        "dongtaiid": "899406249864462368",
        "status": 0
    },
    {
        "dongtaiid": "899405450738401283",
        "status": 0
    },
    {
        "dongtaiid": "899356724596572178",
        "status": 0
    },
    {
        "dongtaiid": "899295448071667717",
        "status": 0
    },
    {
        "dongtaiid": "899295310630617088",
        "status": 0
    },
    {
        "dongtaiid": "899264524302942216",
        "status": 0
    },
    {
        "dongtaiid": "899264361094185014",
        "status": 0
    },
    {
        "dongtaiid": "899052439048552449",
        "status": 0
    },
    {
        "dongtaiid": "898754814770413619",
        "status": 0
    },
    {
        "dongtaiid": "898750790346211346",
        "status": 0
    },
    {
        "dongtaiid": "898750476847153155",
        "status": 0
    },
    {
        "dongtaiid": "898747255630069765",
        "status": 0
    },
    {
        "dongtaiid": "898744932048568374",
        "status": 0
    },
    {
        "dongtaiid": "898744446722506836",
        "status": 0
    },
    {
        "dongtaiid": "898596678354862083",
        "status": 0
    },
    {
        "dongtaiid": "898175307720163350",
        "status": 0
    },
    {
        "dongtaiid": "898175217521655815",
        "status": 0
    },
    {
        "dongtaiid": "897916815112405026",
        "status": 0
    },
    {
        "dongtaiid": "897916664785403908",
        "status": 0
    },
    {
        "dongtaiid": "896860957529079817",
        "status": 0
    },
    {
        "dongtaiid": "896703276381110296",
        "status": 0
    },
    {
        "dongtaiid": "896454322913542161",
        "status": 0
    },
    {
        "dongtaiid": "896374823052115974",
        "status": 0
    },
    {
        "dongtaiid": "896374707073318917",
        "status": 0
    },
    {
        "dongtaiid": "896338882742714385",
        "status": 0
    },
    {
        "dongtaiid": "896338646552018960",
        "status": 0
    },
    {
        "dongtaiid": "896181433535561813",
        "status": 0
    },
    {
        "dongtaiid": "896180815324512310",
        "status": 0
    },
    {
        "dongtaiid": "896150106080804881",
        "status": 0
    },
    {
        "dongtaiid": "895987910924304473",
        "status": 0
    },
    {
        "dongtaiid": "895679730080022593",
        "status": 0
    },
    {
        "dongtaiid": "895679506512084994",
        "status": 0
    },
    {
        "dongtaiid": "895603747574513666",
        "status": 0
    },
    {
        "dongtaiid": "895603528508112899",
        "status": 0
    },
    {
        "dongtaiid": "895424595873497109",
        "status": 0
    },
    {
        "dongtaiid": "895424308110688291",
        "status": 0
    },
    {
        "dongtaiid": "895329522491064337",
        "status": 0
    },
    {
        "dongtaiid": "895029050898120840",
        "status": 0
    },
    {
        "dongtaiid": "894977365263777813",
        "status": 0
    },
    {
        "dongtaiid": "894977240709726216",
        "status": 0
    },
    {
        "dongtaiid": "894974504775712803",
        "status": 0
    },
    {
        "dongtaiid": "894974298617282609",
        "status": 0
    },
    {
        "dongtaiid": "894920486973079572",
        "status": 0
    },
    {
        "dongtaiid": "894918013108617234",
        "status": 0
    },
    {
        "dongtaiid": "894917828425023489",
        "status": 0
    },
    {
        "dongtaiid": "894847640032772130",
        "status": 0
    },
    {
        "dongtaiid": "894847305288515593",
        "status": 0
    },
    {
        "dongtaiid": "894651166791565346",
        "status": 0
    },
    {
        "dongtaiid": "894610562396192802",
        "status": 0
    },
    {
        "dongtaiid": "894545991631372295",
        "status": 0
    },
    {
        "dongtaiid": "894541791151259671",
        "status": 0
    },
    {
        "dongtaiid": "894508015516909621",
        "status": 0
    },
    {
        "dongtaiid": "894481777801822212",
        "status": 0
    },
    {
        "dongtaiid": "894481343746932760",
        "status": 0
    },
    {
        "dongtaiid": "894334434422030336",
        "status": 0
    },
    {
        "dongtaiid": "894328374231564312",
        "status": 0
    }
]